{
  "version": "0.3.14-fixed",
  "steps": [
    {
      "tag": "CreateModel",
      "model": "TenantRegisterVerification"
    },
    {
      "tag": "CreateField",
      "model": "TenantRegisterVerification",
      "field": "id",
      "type": "String",
      "arity": "Required"
    },
    {
      "tag": "CreateDirective",
      "location": {
        "path": {
          "tag": "Field",
          "model": "TenantRegisterVerification",
          "field": "id"
        },
        "directive": "default"
      }
    },
    {
      "tag": "CreateArgument",
      "location": {
        "tag": "Directive",
        "path": {
          "tag": "Field",
          "model": "TenantRegisterVerification",
          "field": "id"
        },
        "directive": "default"
      },
      "argument": "",
      "value": "cuid()"
    },
    {
      "tag": "CreateDirective",
      "location": {
        "path": {
          "tag": "Field",
          "model": "TenantRegisterVerification",
          "field": "id"
        },
        "directive": "id"
      }
    },
    {
      "tag": "CreateField",
      "model": "TenantRegisterVerification",
      "field": "businessInput",
      "type": "String",
      "arity": "Required"
    },
    {
      "tag": "CreateField",
      "model": "TenantRegisterVerification",
      "field": "tenantInput",
      "type": "String",
      "arity": "Required"
    },
    {
      "tag": "CreateField",
      "model": "TenantRegisterVerification",
      "field": "filterInput",
      "type": "String",
      "arity": "Required"
    },
    {
      "tag": "CreateField",
      "model": "TenantRegisterVerification",
      "field": "email",
      "type": "String",
      "arity": "Required"
    },
    {
      "tag": "CreateField",
      "model": "TenantRegisterVerification",
      "field": "verified",
      "type": "Boolean",
      "arity": "Required"
    },
    {
      "tag": "CreateDirective",
      "location": {
        "path": {
          "tag": "Field",
          "model": "TenantRegisterVerification",
          "field": "verified"
        },
        "directive": "default"
      }
    },
    {
      "tag": "CreateArgument",
      "location": {
        "tag": "Directive",
        "path": {
          "tag": "Field",
          "model": "TenantRegisterVerification",
          "field": "verified"
        },
        "directive": "default"
      },
      "argument": "",
      "value": "false"
    },
    {
      "tag": "CreateModel",
      "model": "TenantEmailVerification"
    },
    {
      "tag": "CreateField",
      "model": "TenantEmailVerification",
      "field": "id",
      "type": "String",
      "arity": "Required"
    },
    {
      "tag": "CreateDirective",
      "location": {
        "path": {
          "tag": "Field",
          "model": "TenantEmailVerification",
          "field": "id"
        },
        "directive": "default"
      }
    },
    {
      "tag": "CreateArgument",
      "location": {
        "tag": "Directive",
        "path": {
          "tag": "Field",
          "model": "TenantEmailVerification",
          "field": "id"
        },
        "directive": "default"
      },
      "argument": "",
      "value": "cuid()"
    },
    {
      "tag": "CreateDirective",
      "location": {
        "path": {
          "tag": "Field",
          "model": "TenantEmailVerification",
          "field": "id"
        },
        "directive": "id"
      }
    },
    {
      "tag": "CreateField",
      "model": "TenantEmailVerification",
      "field": "email",
      "type": "String",
      "arity": "Required"
    },
    {
      "tag": "CreateField",
      "model": "TenantEmailVerification",
      "field": "user",
      "type": "TenantUser",
      "arity": "Required"
    },
    {
      "tag": "CreateField",
      "model": "TenantEmailVerification",
      "field": "verified",
      "type": "Boolean",
      "arity": "Required"
    },
    {
      "tag": "CreateDirective",
      "location": {
        "path": {
          "tag": "Field",
          "model": "TenantEmailVerification",
          "field": "verified"
        },
        "directive": "default"
      }
    },
    {
      "tag": "CreateArgument",
      "location": {
        "tag": "Directive",
        "path": {
          "tag": "Field",
          "model": "TenantEmailVerification",
          "field": "verified"
        },
        "directive": "default"
      },
      "argument": "",
      "value": "false"
    },
    {
      "tag": "DeleteModel",
      "model": "TenantVerification"
    },
    {
      "tag": "CreateField",
      "model": "TenantUser",
      "field": "pendingEmail",
      "type": "Boolean",
      "arity": "Required"
    },
    {
      "tag": "CreateDirective",
      "location": {
        "path": {
          "tag": "Field",
          "model": "TenantUser",
          "field": "pendingEmail"
        },
        "directive": "default"
      }
    },
    {
      "tag": "CreateArgument",
      "location": {
        "tag": "Directive",
        "path": {
          "tag": "Field",
          "model": "TenantUser",
          "field": "pendingEmail"
        },
        "directive": "default"
      },
      "argument": "",
      "value": "false"
    }
  ]
}